{
  "hash": "e2c30427",
  "browserHash": "37c42cbc",
  "optimized": {
    "@vuepress/shared": {
      "src": "../../../../node_modules/@vuepress/shared/dist/index.js",
      "file": "@vuepress_shared.js",
      "fileHash": "0ec3e2e6",
      "needsInterop": false
    },
    "vue": {
      "src": "../../../../node_modules/vue/dist/vue.runtime.esm-bundler.js",
      "file": "vue.js",
      "fileHash": "097ff646",
      "needsInterop": false
    },
    "vue-router": {
      "src": "../../../../node_modules/vue-router/dist/vue-router.esm-bundler.js",
      "file": "vue-router.js",
      "fileHash": "bd4b9b2b",
      "needsInterop": false
    }
  },
  "chunks": {
    "chunk-23T3ZXKY": {
      "file": "chunk-23T3ZXKY.js"
    },
    "chunk-OWZTJJDO": {
      "file": "chunk-OWZTJJDO.js"
    }
  }
}